{
    "time": {
        "cpu_time_user": "00:00:06.110",
        "cpu_time_system": "00:00:01.850",
        "runtime": "00:00:09.984",
        "cpu_time_iowait": "00:00:00.000"
    },
    "peak_resources": {
        "cpu_percent": 139.1,
        "memory_rss": "1GiB",
        "memory_vms": "2GiB",
        "threads": 2
    },
    "avg_resources": {
        "cpu_percent": 78.17821782178214,
        "memory_rss": "569MiB",
        "memory_vms": "868MiB",
        "threads": 1.9207920792079207
    }
}